{
    "bulletin": "夏日炎炎，攻城別忘了補充水分！",
    "regulations": [
        "當使用者(以下稱攻城師)開始使用本應用程式(以下稱攻城GO)的相關功能時，即表示其已詳閱及同意本頁面所載之全部相關注意事項。",
        "攻城GO現階段為提供台灣地區攻城師下載及使用之應用程式，攻城GO作者與日本城郭協會(公益財団法人日本城郭協会)並無任何關聯。",
        "攻城GO為幫助攻城師記錄其日本100名城集章歷程之應用程式，請攻城師務必將各城郭印章蓋在其所攜帶之日本城郭協會認定的公式集章冊內(詳見常見攻城問題)，再將其拍照並裁切後設定於攻城及修改頁面內。",
        "攻城GO內所記載之各城郭的蓋章地點資訊，包括其名稱(中文及日文)、地圖座標、官方網站連結及下方備註欄文字皆僅供參考，攻城GO雖會不定期對其進行確認及更新，但不對其正確性及時效性負任何責任。",
        "攻城GO的常見攻城問題頁面列出一些與蓋章相關的Q & A，提供給攻城師參考，惟攻城GO不對其正確性負任何責任。",
        "攻城師之所有攻城記錄皆儲存於其裝置內，若攻城師自行刪除(解除安裝)攻城GO或因其他不明原因造成攻城GO從裝置中被移除，其所有記錄將跟著應用程式一併刪除。建議攻城師若有此方面的疑慮，請另行備份其印章圖片及蓋章日期等攻城記錄，攻城GO不對攻城師之攻城記錄負任何責任。",
        "攻城GO內導覽及使用流程介紹內所出現之印章圖片純屬範例用，並非實際日本100名城集章活動之印章。攻城師於蓋章時需自行留意與確認眼前印章是否為日本100名城集章活動之印章。",
        "攻城GO若因故將於App Store下架應用程式，將提前30日公告於載入(開啟)畫面或以其他方式告知，但攻城GO作者仍保留無預警下架攻城GO之權利。",
        "本頁面所載之相關注意事項將不定期調整與更新，更新時將公告於攻城GO之載入(開啟)畫面，並於本頁面最下方顯示更新日期。",
        "攻城GO作者保有以上相關注意事項之最終解釋權。"
    ],
    "regulationsUpadteDate": "2024年09月05日",
    "iconSourcesName": [
        "底部名城集章冊圖示(From Icon-rainbow)",
        "底部百名城地圖圖示(From Flaticon)",
        "底部攻城師本陣圖示(From Icon-rainbow)",
        "尚未攻略預設圖片(From 素材Library)",
        "名城集章冊預設背景(From illustAC)",
        "各城地圖印章設置地點圖示(From icons8)",
        "各城地圖城郭位置圖示(From Icon-rainbow)",
        "百名城地圖內各城郭圖示(From Icon-rainbow)",
        "攻城難易度圖示Level 1(From icons8)",
        "攻城難易度圖示Level 2(From icons8)",
        "攻城難易度圖示Level 3(From icons8)",
        "攻城難易度圖示Level 4(From icons8)",
        "攻城難易度圖示Level 5(From icons8)",
        "字型-jf open 粉圓體",
        "字型-正風毛筆MasaFont",
        "字型-衡山毛筆フォント行書",
        "字型-青柳隷書aoyagireisyosimo2",
        "字型-Oradano-mincho-GSRR"
    ],
    "iconSourcesUrl": [
        "https://icon-rainbow.com/%e3%81%8a%e5%9f%8e%e3%81%ae%e7%84%a1%e6%96%99%e3%82%a2%e3%82%a4%e3%82%b3%e3%83%b3%e7%b4%a0%e6%9d%90-1/",
        "https://www.flaticon.com/free-icon/pin_2711637?term=location+mark&page=1&position=6&origin=tag&related_id=2711637",
        "https://icon-rainbow.com/%E6%97%A5%E6%9C%AC%E3%81%AE%E5%85%9C%E3%81%AE%E7%84%A1%E6%96%99%E3%82%A2%E3%82%A4%E3%82%B3%E3%83%B3%E7%B4%A0%E6%9D%90-2/",
        "https://www.sozai-library.com/sozai/9269",
        "https://zh-tw.ac-illust.com/clip-art/456257",
        "https://icons8.jp/icon/sflHBTeKu7ZQ/%E3%83%93%E3%82%B6%E3%82%B9%E3%82%BF%E3%83%B3%E3%83%97",
        "https://icon-rainbow.com/%e3%81%8a%e5%9f%8e%e3%81%ae%e7%84%a1%e6%96%99%e3%82%a2%e3%82%a4%e3%82%b3%e3%83%b3%e7%b4%a0%e6%9d%90-1/",
        "https://icon-rainbow.com/%e3%81%8a%e5%9f%8e%e3%81%ae%e7%84%a1%e6%96%99%e3%82%a2%e3%82%a4%e3%82%b3%e3%83%b3%e7%b4%a0%e6%9d%90-2/",
        "https://icons8.jp/icon/4dTBn5vlN-an/%E3%82%AA%E3%82%BF%E3%82%AF%E9%A1%94",
        "https://icons8.jp/icon/CI35yofl8J6k/%E3%81%AB%E3%82%84%E3%81%AB%E3%82%84%E9%A1%94",
        "https://icons8.jp/icon/OPExqLhGyqfH/expressionless-face",
        "https://icons8.jp/icon/-0qLLnx1h2qn/confounded-face",
        "https://icons8.jp/icon/QEwudVFixKnU/tired-face",
        "https://justfont.com/huninn/",
        "https://github.com/max32002/masafont",
        "https://opentype.jp/kouzangyousho.htm",
        "http://www.ziti.net.cn/mianfeiziti/1122.html",
        "http://www.ziti.net.cn/mianfeiziti/1223.html"
    ],
    "latestVersion": "1.0"
}
